{
  "Title": "How Ordered Is It? On the Perceptual Orderability of Visual Channels",
  "Category": "Experiment",
  "Authors": "David H. S. Chung, Daniel Archambault, Rita Borgo, Darren J. Edwards, Robert S. Laramee, Min Chen",
  "Link": "https://dl.acm.org/doi/10.5555/3071534.3071550",
  "Designs": {
    "E-1": {
      "fields": [
        {
          "name": "n",
          "type": "string",
          "interesting": "true"
        },
        {
          "name": "q",
          "type": "number",
          "interesting": "true"
        }
      ],
      "design": {
        "coordinates": "cartesian",
        "mark": "point",
        "encoding": {
          "x": {
            "field": "n",
            "type": "nominal"
          },
          "color": {
            "field": "q",
            "type": "quantitative"
          }
        }
      }
    },
    "E-2": {
      "fields": [
        {
          "name": "n",
          "type": "string",
          "interesting": "true"
        },
        {
          "name": "q",
          "type": "number",
          "interesting": "true"
        }
      ],
      "design": {
        "coordinates": "cartesian",
        "mark": "point",
        "encoding": {
          "x": {
            "field": "n",
            "type": "nominal"
          },
          "size": {
            "field": "q",
            "type": "quantitative"
          }
        }
      }
    },
    "E-3": {
      "fields": [
        {
          "name": "n",
          "type": "string",
          "interesting": "true"
        },
        {
          "name": "q",
          "type": "number",
          "interesting": "true"
        }
      ],
      "design": {
        "coordinates": "cartesian",
        "mark": "point",
        "encoding": {
          "x": {
            "field": "n",
            "type": "nominal"
          },
          "color": {
            "field": "q",
            "type": "nominal"
          }
        }
      }
    },
    "E-6": {
      "fields": [
        {
          "name": "n",
          "type": "string",
          "interesting": "true"
        },
        {
          "name": "q",
          "type": "number",
          "interesting": "true"
        }
      ],
      "design": {
        "coordinates": "cartesian",
        "mark": "point",
        "encoding": {
          "x": {
            "field": "n",
            "type": "nominal"
          },
          "shape": {
            "field": "q",
            "type": "ordinal"
          }
        }
      }
    },
    "E-7": {
      "fields": [
        {
          "name": "n",
          "type": "string",
          "interesting": "true"
        },
        {
          "name": "q",
          "type": "number",
          "interesting": "true"
        }
      ],
      "design": {
        "coordinates": "cartesian",
        "mark": "text",
        "encoding": {
          "x": {
            "field": "n",
            "type": "nominal"
          },
          "text": {
            "field": "q",
            "type": "quantitative"
          }
        }
      }
    }
  },
  "Tasks": ["correlate", "find-extremum"],
  "Results": {
    "Experimental": {
      "accuracy": {
        "correlate": {
          "rank": ["E-1", "E-4", "E-6", "E-2", "E-5", "E-3", "E-7"],
          "significance": [
            ["E-1", "E-2"],
            ["E-1", "E-3"],
            ["E-1", "E-5"],
            ["E-1", "E-7"],
            ["E-4", "E-2"],
            ["E-4", "E-3"],
            ["E-4", "E-5"],
            ["E-4", "E-7"],
            ["E-6", "E-3"],
            ["E-6", "E-7"],
            ["E-2", "E-7"],
            ["E-5", "E-7"]
          ],
          "pvalue": 0.05
        },
        "find-extremum": {
          "rank": ["E-7", "E-2", "E-6", "E-4", "E-1", "E-5", "E-3"],
          "significance": [
            ["E-7", "E-6"],
            ["E-7", "E-4"],
            ["E-7", "E-1"],
            ["E-7", "E-5"],
            ["E-7", "E-3"],
            ["E-2", "E-6"],
            ["E-2", "E-4"],
            ["E-2", "E-1"],
            ["E-2", "E-5"],
            ["E-2", "E-3"],
            ["E-6", "E-5"],
            ["E-6", "E-3"],
            ["E-4", "E-5"],
            ["E-4", "E-3"],
            ["E-1", "E-5"],
            ["E-1", "E-3"]
          ],
          "pvalue": 0.05
        }
      },
      "time": {
        "correlate": {
          "rank": ["E-2", "E-5", "E-1", "E-4", "E-3", "E-6", "E-7"],
          "significance": [
            ["E-2", "E-4"],
            ["E-2", "E-3"],
            ["E-2", "E-6"],
            ["E-2", "E-7"],
            ["E-5", "E-4"],
            ["E-5", "E-6"],
            ["E-5", "E-7"],
            ["E-1", "E-4"],
            ["E-1", "E-6"],
            ["E-1", "E-7"],
            ["E-4", "E-6"],
            ["E-4", "E-7"],
            ["E-3", "E-6"],
            ["E-3", "E-7"]
          ],
          "pvalue": 0.05
        },
        "find-extremum": {
          "rank": ["E-1", "E-5", "E-4", "E-3", "E-2", "E-6", "E-7"],
          "significance": [
            ["E-1", "E-6"],
            ["E-1", "E-7"],
            ["E-5", "E-6"],
            ["E-5", "E-7"],
            ["E-4", "E-6"],
            ["E-4", "E-7"],
            ["E-3", "E-6"],
            ["E-3", "E-7"],
            ["E-2", "E-6"],
            ["E-2", "E-7"]
          ],
          "pvalue": 0.05
        }
      }
    }
  }
}
